asiva/__init__.py
asiva/app.py
asiva/asiva.py
asiva/src/__init__.py
asiva/src/aboutUs.py
asiva/src/classifyVariables.py
asiva/src/dataProcessing.py
asiva/src/dataReduction.py
asiva/src/featureExtraction.py
asiva/src/home.py
asiva/src/periodDetection.py
asiva/src/stationarityTest.py
asiva/src/variabledetection.py
asiva/src/features/__init__.py
asiva/src/features/allFeatures.py
asiva/src/features/customFeatures.py
asiva/src/features/modelFeatures.py
asiva/src/model/__init__.py
asiva/src/model/animated.gif
asiva/src/model/asivaRF_cm.png
asiva/src/model/asivaRF_model.joblib
asiva/src/model/assets.py
asiva/src/model/logo.png
asiva/src/model/old_animated.gif
asiva-1.6.0.dist-info/LICENSE
asiva-1.6.0.dist-info/METADATA
asiva-1.6.0.dist-info/WHEEL
asiva-1.6.0.dist-info/top_level.txt
asiva-1.6.0.dist-info/RECORD
