Metadata-Version: 2.1
Name: asiva
Version: 1.6.0
Summary: Platform for Observational and Computational Analysis of Stellar Variables
Home-page: UNKNOWN
Author: P. Saleh & T. Singh
License: MIT
Platform: UNKNOWN
License-File: LICENSE
Requires-Dist: astropy (==4.2.1)
Requires-Dist: asivaflow
Requires-Dist: config (==0.5.1)
Requires-Dist: gatspy (==0.3)
Requires-Dist: joblib
Requires-Dist: matplotlib (==3.3.4)
Requires-Dist: mplcursors
Requires-Dist: nolds (==0.5.2)
Requires-Dist: numpy (==1.21.6)
Requires-Dist: pandas (==1.3.5)
Requires-Dist: PyQt5 (==5.15.7)
Requires-Dist: pyts (==0.12.0)
Requires-Dist: QtAwesome (==1.0.2)
Requires-Dist: scikit-learn (==1.2.0)
Requires-Dist: scipy (==1.6.2)
Requires-Dist: seaborn (==0.11.1)
Requires-Dist: statsmodels (==0.12.2)
